rxnDB/__init__.py
rxnDB/app.py
rxnDB/cli.py
rxnDB/requirements.txt
rxnDB/styles.css
rxnDB/ui.py
rxnDB/utils.py
rxnDB/visualize.py
rxnDB/data/__init__.py
rxnDB/data/loader.py
rxnDB/data/mapping.py
rxnDB/data/preprocessor.py
rxnDB/data/processor.py
rxnDB/data/cache/rxnDB.parquet
rxnDB/data/sets/hp11-raw.txt
rxnDB/data/sets/hp11/hp11-001.yml
rxnDB/data/sets/hp11/hp11-002.yml
rxnDB/data/sets/hp11/hp11-003.yml
rxnDB/data/sets/hp11/hp11-004.yml
rxnDB/data/sets/hp11/hp11-005.yml
rxnDB/data/sets/hp11/hp11-006.yml
rxnDB/data/sets/hp11/hp11-007.yml
rxnDB/data/sets/hp11/hp11-008.yml
rxnDB/data/sets/hp11/hp11-009.yml
rxnDB/data/sets/hp11/hp11-010.yml
rxnDB/data/sets/hp11/hp11-011.yml
rxnDB/data/sets/hp11/hp11-012.yml
rxnDB/data/sets/hp11/hp11-013.yml
rxnDB/data/sets/hp11/hp11-014.yml
rxnDB/data/sets/hp11/hp11-015.yml
rxnDB/data/sets/hp11/hp11-016.yml
rxnDB/data/sets/hp11/hp11-017.yml
rxnDB/data/sets/hp11/hp11-018.yml
rxnDB/data/sets/hp11/hp11-019.yml
rxnDB/data/sets/hp11/hp11-020.yml
rxnDB/data/sets/hp11/hp11-021.yml
rxnDB/data/sets/hp11/hp11-022.yml
rxnDB/data/sets/hp11/hp11-023.yml
rxnDB/data/sets/hp11/hp11-024.yml
rxnDB/data/sets/hp11/hp11-025.yml
rxnDB/data/sets/hp11/hp11-026.yml
rxnDB/data/sets/hp11/hp11-027.yml
rxnDB/data/sets/hp11/hp11-028.yml
rxnDB/data/sets/hp11/hp11-029.yml
rxnDB/data/sets/hp11/hp11-030.yml
rxnDB/data/sets/hp11/hp11-031.yml
rxnDB/data/sets/hp11/hp11-032.yml
rxnDB/data/sets/hp11/hp11-033.yml
rxnDB/data/sets/hp11/hp11-034.yml
rxnDB/data/sets/hp11/hp11-035.yml
rxnDB/data/sets/hp11/hp11-036.yml
rxnDB/data/sets/hp11/hp11-037.yml
rxnDB/data/sets/hp11/hp11-038.yml
rxnDB/data/sets/hp11/hp11-039.yml
rxnDB/data/sets/hp11/hp11-040.yml
rxnDB/data/sets/hp11/hp11-041.yml
rxnDB/data/sets/hp11/hp11-042.yml
rxnDB/data/sets/hp11/hp11-043.yml
rxnDB/data/sets/hp11/hp11-044.yml
rxnDB/data/sets/hp11/hp11-045.yml
rxnDB/data/sets/hp11/hp11-046.yml
rxnDB/data/sets/hp11/hp11-047.yml
rxnDB/data/sets/hp11/hp11-048.yml
rxnDB/data/sets/hp11/hp11-049.yml
rxndb-0.1.0a23.dist-info/licenses/LICENSE
rxndb-0.1.0a23.dist-info/METADATA
rxndb-0.1.0a23.dist-info/WHEEL
rxndb-0.1.0a23.dist-info/entry_points.txt
rxndb-0.1.0a23.dist-info/top_level.txt
rxndb-0.1.0a23.dist-info/RECORD
