Metadata-Version: 2.4
Name: rxnDB
Version: 0.1.0a23
Summary: A Python Shiny app for reaction database management
Author-email: Buchanan Kerswell <buck.kerswell@gmail.com>
License: MIT
Project-URL: Repository, https://github.com/buchanankerswell/kerswell_et_al_rxnDB
Classifier: Natural Language :: English
Classifier: Development Status :: 2 - Pre-Alpha
Classifier: Intended Audience :: Science/Research
Classifier: Programming Language :: Python :: 3
Classifier: License :: OSI Approved :: MIT License
Classifier: Operating System :: OS Independent
Classifier: Topic :: Scientific/Engineering :: Visualization
Requires-Python: >=3.10
License-File: LICENSE
Requires-Dist: shiny
Requires-Dist: shinywidgets
Requires-Dist: anywidget
Requires-Dist: pandas
Requires-Dist: plotly
Requires-Dist: ruamel.yaml
Requires-Dist: fastparquet
Requires-Dist: faicons
Provides-Extra: dev
Requires-Dist: pytest; extra == "dev"
Requires-Dist: pip; extra == "dev"
Requires-Dist: pytest-cov; extra == "dev"
Requires-Dist: pandas-stubs; extra == "dev"
Requires-Dist: shinylive; extra == "dev"
Dynamic: license-file
